{"asset": {                "version": "0.0",                "gltfUpAxis": "Y"            },            "geometricError":100.000000,"root": {                "transform": [-0.882244,-0.470792,0.000000,0.000000,0.193686,-0.362959,0.911453,0.000000,-0.428615,0.803205,0.413704,0.000000,-2735331.415816,5125888.137422,2622501.374547,1],                "boundingVolume": {                    "region": [2.060912,0.426480,2.061058,0.426558,0.000000,300.000000]},"geometricError": 100.000000,                        "refine": "REPLACE",                        "content": {                            "uri": "./tile/4/3/2.b3dm"}}}